tgeraser/__init__.py
tgeraser/__main__.py
tgeraser/__version__.py
tgeraser/core.py
tgeraser/eraser.py
tgeraser/exceptions.py
tgeraser/utils.py
tgeraser-1.4.2.dist-info/licenses/LICENSE
tgeraser-1.4.2.dist-info/METADATA
tgeraser-1.4.2.dist-info/WHEEL
tgeraser-1.4.2.dist-info/entry_points.txt
tgeraser-1.4.2.dist-info/top_level.txt
tgeraser-1.4.2.dist-info/RECORD
