Metadata-Version: 2.4
Name: tgeraser
Version: 1.4.2
Summary: Tool deletes all your messages from chat/channel/conversation on Telegram.
Home-page: https://github.com/en9inerd/tgeraser
Author: Vladimir Loskutov
Author-email: vladimir@enginerd.io
License: MIT License
Keywords: telegram,api,delete messages
Classifier: Programming Language :: Python
Classifier: Programming Language :: Python :: 3.8
Classifier: Programming Language :: Python :: 3.9
Classifier: Programming Language :: Python :: 3.10
Classifier: Programming Language :: Python :: 3.11
Classifier: License :: OSI Approved :: MIT License
Requires-Python: <4,>=3.8
License-File: LICENSE
Requires-Dist: docopt
Requires-Dist: pyaes
Requires-Dist: pyasn1
Requires-Dist: rsa
Requires-Dist: telethon>=1.32.0
Dynamic: license-file
